nacos/__init__.py
nacos/client.py
nacos/commons.py
nacos/exception.py
nacos/files.py
nacos/listener.py
nacos/params.py
nacos/timer.py
nacos_newsdk_python-0.1.16.dist-info/LICENSE
nacos_newsdk_python-0.1.16.dist-info/METADATA
nacos_newsdk_python-0.1.16.dist-info/WHEEL
nacos_newsdk_python-0.1.16.dist-info/top_level.txt
nacos_newsdk_python-0.1.16.dist-info/RECORD
