Metadata-Version: 2.1
Name: nacos-newsdk-python
Version: 0.1.16
Summary: A New Python client updated for Nacos.
Home-page: https://github.com/nacos-group/nacos-sdk-python
Author: Mark
Author-email: sihengshen@foxmail.com
License: Apache License 2.0
Project-URL: Documentation, https://github.com/nacos-group/nacos-sdk-python
Project-URL: Source, https://github.com/nacos-group/nacos-sdk-python
Project-URL: Nacos Open API Guide, https://nacos.io/en-us/docs/open-api.html
Keywords: nacos,nacos-sdk-python,nacos-newsdk-python
Classifier: Topic :: Software Development :: Libraries :: Python Modules
Classifier: Operating System :: OS Independent
Classifier: Programming Language :: Python
Classifier: Programming Language :: Python :: 2.7
Classifier: Programming Language :: Python :: 3.6
Classifier: Programming Language :: Python :: 3.7
License-File: LICENSE
